{
	"c1TUr40M.anybfans.anyb.tk" : {
		"totalUploadBytes" : 1319001,
		"totalDownloadBytes" : 58296431
	},
	"45.32.76.241" : {
		"totalUploadBytes" : 21838660,
		"totalDownloadBytes" : 388140708
	},
	"23.106.152.12" : {
		"totalUploadBytes" : 2783195,
		"totalDownloadBytes" : 134105512
	},
	"107.182.177.192" : {
		"totalUploadBytes" : 13157,
		"totalDownloadBytes" : 0
	},
	"jp.ioss.pw" : {
		"totalUploadBytes" : 1153520,
		"totalDownloadBytes" : 50052033
	},
	"us.ioss.pw" : {
		"totalUploadBytes" : 43383,
		"totalDownloadBytes" : 1377510
	},
	"usa.ioss.pw" : {
		"totalUploadBytes" : 55647,
		"totalDownloadBytes" : 1681574
	}
}